tenb2jira/__init__.py
tenb2jira/cli.py
tenb2jira/models.py
tenb2jira/processor.py
tenb2jira/validator.py
tenb2jira/version.py
tenb2jira/jira/__init__.py
tenb2jira/jira/field.py
tenb2jira/jira/jira.py
tenb2jira/jira/task.py
tenb2jira/jira/api/__init__.py
tenb2jira/jira/api/fields.py
tenb2jira/jira/api/issues.py
tenb2jira/jira/api/issuetypes.py
tenb2jira/jira/api/iterator.py
tenb2jira/jira/api/projects.py
tenb2jira/jira/api/screens.py
tenb2jira/jira/api/session.py
tenb2jira/tenable/__init__.py
tenb2jira/tenable/generators.py
tenb2jira/tenable/tenable.py
tenb2jira-2.1.0.dist-info/METADATA
tenb2jira-2.1.0.dist-info/WHEEL
tenb2jira-2.1.0.dist-info/entry_points.txt
tenb2jira-2.1.0.dist-info/top_level.txt
tenb2jira-2.1.0.dist-info/RECORD
