Metadata-Version: 2.4
Name: tenb2jira
Version: 2.1.0
Summary: Tenable Vulnerability Management to Jira Cloud issue manager
Author-email: "Tenable, Inc." <smcgrath@tenable.com>
License: MIT License
Project-URL: Homepage, https://github.com/tenable/integration-jira-cloud
Project-URL: Repository, https://github.com/tenable/integration-jira-cloud
Project-URL: Issues, https://github.com/tenable/integration-jira-cloud/issues
Project-URL: Changelog, https://github.com/tenable/integration-jira-cloud/blob/master/CHANGELOG.md
Keywords: tenable,tenable vulnerability management,tenable security center,tenable.io,tenable.sc,jira,jira cloud
Classifier: Development Status :: 5 - Production/Stable
Classifier: Intended Audience :: Information Technology
Classifier: Topic :: System :: Systems Administration
Classifier: License :: OSI Approved :: MIT License
Classifier: Programming Language :: Python :: 3.10
Classifier: Programming Language :: Python :: 3.11
Classifier: Programming Language :: Python :: 3.12
Requires-Dist: arrow>=1.3.0
Requires-Dist: restfly>=1.4.5
Requires-Dist: typer>=0.9.0
Requires-Dist: tomlkit>=0.12.4
Requires-Dist: rich>=13.3.1
Requires-Dist: pytenable>=1.8.3
Requires-Dist: SQLAlchemy>=2.0.28
Requires-Dist: pydantic>=2.7.1
